{
  "openapi": "3.0.1",
  "info": {
    "title": "PROJETO_PAN",
    "version": "1.0"
  },
  "paths": {
    "/api/Usuario": {
      "get": {
        "tags": [
          "Usuario"
        ],
        "responses": {
          "200": {
            "description": "OK"
          }
        }
      },
      "post": {
        "tags": [
          "Usuario"
        ],
        "requestBody": {
          "content": {
            "application/json": {
              "schema": {
                "$ref": "#/components/schemas/UsuarioCriarDTO"
              }
            },
            "text/json": {
              "schema": {
                "$ref": "#/components/schemas/UsuarioCriarDTO"
              }
            },
            "application/*+json": {
              "schema": {
                "$ref": "#/components/schemas/UsuarioCriarDTO"
              }
            }
          }
        },
        "responses": {
          "200": {
            "description": "OK"
          }
        }
      },
      "put": {
        "tags": [
          "Usuario"
        ],
        "requestBody": {
          "content": {
            "application/json": {
              "schema": {
                "$ref": "#/components/schemas/UsuarioListarDTO"
              }
            },
            "text/json": {
              "schema": {
                "$ref": "#/components/schemas/UsuarioListarDTO"
              }
            },
            "application/*+json": {
              "schema": {
                "$ref": "#/components/schemas/UsuarioListarDTO"
              }
            }
          }
        },
        "responses": {
          "200": {
            "description": "OK"
          }
        }
      },
      "delete": {
        "tags": [
          "Usuario"
        ],
        "parameters": [
          {
            "name": "usuarioId",
            "in": "query",
            "schema": {
              "type": "integer",
              "format": "int32"
            }
          }
        ],
        "responses": {
          "200": {
            "description": "OK"
          }
        }
      }
    },
    "/api/Usuario/{usuarioId}": {
      "get": {
        "tags": [
          "Usuario"
        ],
        "parameters": [
          {
            "name": "usuarioId",
            "in": "path",
            "required": true,
            "schema": {
              "type": "integer",
              "format": "int32"
            }
          }
        ],
        "responses": {
          "200": {
            "description": "OK"
          }
        }
      }
    }
  },
  "components": {
    "schemas": {
      "UsuarioCriarDTO": {
        "type": "object",
        "properties": {
          "nomeCompleto": {
            "type": "string",
            "nullable": true
          },
          "email": {
            "type": "string",
            "nullable": true
          },
          "cpf": {
            "type": "string",
            "nullable": true
          },
          "situacao": {
            "type": "boolean"
          }
        },
        "additionalProperties": false
      },
      "UsuarioListarDTO": {
        "type": "object",
        "properties": {
          "id": {
            "type": "integer",
            "format": "int32"
          },
          "nomeCompleto": {
            "type": "string",
            "nullable": true
          },
          "email": {
            "type": "string",
            "nullable": true
          },
          "situacao": {
            "type": "boolean"
          }
        },
        "additionalProperties": false
      }
    }
  }
}